voduploadsdk/AliyunVodUploader.py
voduploadsdk/AliyunVodUtils.py
voduploadsdk/UploadAttachedMediaRequest.py
voduploadsdk/UploadImageRequest.py
voduploadsdk/UploadVideoRequest.py
voduploadsdk/__init__.py
voduploadsdk-1.0.2.dist-info/METADATA
voduploadsdk-1.0.2.dist-info/WHEEL
voduploadsdk-1.0.2.dist-info/top_level.txt
voduploadsdk-1.0.2.dist-info/RECORD
