Metadata-Version: 2.1
Name: voduploadsdk
Version: 1.0.2
Summary: Aliyun Vod upload SDK
Home-page: UNKNOWN
Author: UNKNOWN
Author-email: UNKNOWN
License: UNKNOWN
Platform: UNKNOWN
Requires-Dist: aliyun-python-sdk-core-v3
Requires-Dist: aliyun-python-sdk-vod
